gh_auto/main.py
gh_auto/commands/repo.py
gh_auto/helpers/authentication.py
cli_gh_auto-0.0.1.dist-info/LICENCE.md
cli_gh_auto-0.0.1.dist-info/METADATA
cli_gh_auto-0.0.1.dist-info/WHEEL
cli_gh_auto-0.0.1.dist-info/entry_points.txt
cli_gh_auto-0.0.1.dist-info/top_level.txt
cli_gh_auto-0.0.1.dist-info/RECORD
