Metadata-Version: 2.1
Name: cli-gh-auto
Version: 0.0.1
Summary: A cli-tool that will speed up your github workflow!
Home-page: https://github.com/JefvdA/gh-auto
Author: JefvdA
Author-email: jef.v.d.a@live.be
Project-URL: Bug Tracker, https://github.com/JefvdA/gh-auto/issues
Classifier: Programming Language :: Python :: 3
Classifier: License :: OSI Approved :: MIT License
Classifier: Operating System :: OS Independent
License-File: LICENCE.md
Requires-Dist: typer[all]
Requires-Dist: requests
